LICENSE
calendarutils/__init__.py
calendarutils/calendarstats.py
calendarutils/config.py
calendarutils/create_oncall_cal_events.py
calendar_utils-1.0.1.dist-info/LICENSE
calendar_utils-1.0.1.dist-info/METADATA
calendar_utils-1.0.1.dist-info/WHEEL
calendar_utils-1.0.1.dist-info/RECORD
