Metadata-Version: 2.1
Name: calendar-utils
Version: 1.0.1
Summary: 
Home-page: https://github.com/szilard-nemeth/calendar-utils
Keywords: calendar utils
Author: Szilard Nemeth
Author-email: szilard.nemeth88@gmail.com
Requires-Python: >=3.8.12,<4.0.0
Classifier: Programming Language :: Python :: 3
Classifier: Programming Language :: Python :: 3.9
Classifier: Programming Language :: Python :: 3.10
Classifier: Programming Language :: Python :: 3.11
Classifier: Programming Language :: Python :: 3.12
Requires-Dist: google-api-wrapper2 (==1.0.9)
Requires-Dist: icalendar (==5.0.11)
Requires-Dist: python-common-lib (==1.0.9)
Requires-Dist: requests
Project-URL: Repository, https://github.com/szilard-nemeth/calendar-utils
